sql_convertor/__init__.py
sql_convertor/cli.py
sql_convertor/dest/__init__.py
sql_convertor/dest/base.py
sql_convertor/dest/factory.py
sql_convertor/dest/peewee.py
sql_convertor/source/__init__.py
sql_convertor/source/base.py
sql_convertor/source/factory.py
sql_convertor/source/sql/__init__.py
sql_convertor/source/sql/helper.py
sql_convertor/source/sql/parser.py
sql_convertor/tests/__init__.py
sql_convertor/tests/base.py
sql_convertor/tests/test_peewee_emit.py
sql_convertor/tests/test_sql_parser.py
sql_convertor-0.0.8.dist-info/entry_points.txt
sql_convertor-0.0.8.dist-info/LICENSE
sql_convertor-0.0.8.dist-info/WHEEL
sql_convertor-0.0.8.dist-info/METADATA
sql_convertor-0.0.8.dist-info/RECORD
